teledapps/__init__.py
teledapps/actions.py
teledapps/bot.py
teledapps/callback_data.py
teledapps/platform/__init__.py
teledapps/platform/categories.py
teledapps/platform/connector.py
teledapps/platform/helpers/__init__.py
teledapps/platform/helpers/keyboards.py
teledapps/platform/passport.py
teledapps/platform/platform.py
teledapps/tokenlists/__init__.py
teledapps/tokenlists/lists/1inch.json
teledapps/tokenlists/lists/coingecko.json
teledapps/tokenlists/lists/uniswap.json
teledapps/utils/__init__.py
teledapps/utils/logger.py
teledapps-0.2.5.dist-info/WHEEL
teledapps-0.2.5.dist-info/METADATA
teledapps-0.2.5.dist-info/RECORD
