Metadata-Version: 2.1
Name: teledapps
Version: 0.2.5
Summary: Python package for building Telegram bots, compatible with Teledapps
Author: Sergey P
Author-email: pavlovdog.moscow@gmail.com
Requires-Python: >=3.8,<4.0
Classifier: Programming Language :: Python :: 3
Classifier: Programming Language :: Python :: 3.8
Classifier: Programming Language :: Python :: 3.9
Requires-Dist: attrdict (>=2.0.1,<3.0.0)
Requires-Dist: python-telegram-bot (>=13.3,<14.0)
Requires-Dist: web3 (>=5.17.0,<6.0.0)
